{
	"name": "ds_SomFoodPrices_copied",
	"properties": {
		"linkedServiceName": {
			"referenceName": "ls_injectionsa",
			"type": "LinkedServiceReference"
		},
		"parameters": {
			"datasetFileName": {
				"type": "string",
				"defaultValue": "SomFoodPrices_copied"
			}
		},
		"annotations": [],
		"type": "DelimitedText",
		"typeProperties": {
			"location": {
				"type": "AzureBlobStorageLocation",
				"fileName": {
					"value": "@dataset().datasetFileName",
					"type": "Expression"
				},
				"folderPath": "copied",
				"container": "datakind"
			},
			"columnDelimiter": ",",
			"escapeChar": "\\",
			"firstRowAsHeader": true,
			"quoteChar": "\""
		},
		"schema": []
	}
}